pyDSA_gui/MPLWidget.py
pyDSA_gui/MainApp.py
pyDSA_gui/__init__.py
pyDSA_gui/design.py
pyDSA_gui/dsa_backend.py
pyDSA_gui/files_helper.py
pyDSA_gui/log.py
pyDSA_gui/mpl_handlers.py
pyDSA_gui/tab.py
pyDSA_gui/tabanalyze.py
pyDSA_gui/tabdata.py
pyDSA_gui/tabedges.py
pyDSA_gui/tabfits.py
pyDSA_gui/tabimport.py
pyDSA_gui-1.5.4.dist-info/LICENSE
pyDSA_gui-1.5.4.dist-info/METADATA
pyDSA_gui-1.5.4.dist-info/WHEEL
pyDSA_gui-1.5.4.dist-info/entry_points.txt
pyDSA_gui-1.5.4.dist-info/top_level.txt
pyDSA_gui-1.5.4.dist-info/RECORD
