Metadata-Version: 2.1
Name: pyDSA_gui
Version: 1.5.4
Summary: GUI for pyDSA_core
Home-page: https://framagit.org/gabylaunay/pyDSA_gui
Author: Gaby Launay
Author-email: gaby.launay@protonmail.com
Keywords: GUI DSA drop shape contact angle hysteresis
Classifier: Development Status :: 5 - Production/Stable
Classifier: Intended Audience :: Science/Research
Classifier: Topic :: Scientific/Engineering
Classifier: Programming Language :: Python :: 3.5
Classifier: Natural Language :: English
Classifier: License :: OSI Approved :: GNU General Public License v3 (GPLv3)
Classifier: Operating System :: POSIX :: Linux
License-File: LICENSE
Requires-Dist: pyQt5
Requires-Dist: pyDSA-core ==1.4.1
Requires-Dist: numpy
Requires-Dist: matplotlib >=2.2.0
Requires-Dist: xlsxwriter
